jakteristics/__about__.py
jakteristics/__init__.py
jakteristics/__main__.py
jakteristics/constants.py
jakteristics/extension.cp310-win_amd64.pyd
jakteristics/extension.cpp
jakteristics/extension.pyx
jakteristics/las_utils.py
jakteristics/main.py
jakteristics/utils.cp310-win_amd64.pyd
jakteristics/utils.cpp
jakteristics/utils.pxd
jakteristics/utils.pyx
jakteristics/ckdtree/ckdtree.cp310-win_amd64.pyd
jakteristics-0.6.2.dist-info/METADATA
jakteristics-0.6.2.dist-info/WHEEL
jakteristics-0.6.2.dist-info/entry_points.txt
jakteristics-0.6.2.dist-info/top_level.txt
jakteristics-0.6.2.dist-info/RECORD
