Metadata-Version: 1.2
Name: jakteristics
Version: 0.6.2
Summary: Point cloud geometric properties from python.
Home-page: https://github.com/jakarto3d/jakteristics
Author: David Caron
Author-email: david.caron@jakarto.com
License: BSD
Keywords: jakteristics
Platform: UNKNOWN
Classifier: Development Status :: 2 - Pre-Alpha
Classifier: Intended Audience :: Developers
Classifier: License :: OSI Approved :: BSD License
Classifier: Natural Language :: English
Classifier: Programming Language :: Cython
Classifier: Programming Language :: Python :: 3
Classifier: Programming Language :: Python :: 3.8
Requires-Python: >=3.7
